firex_keeper/__init__.py
firex_keeper/__main__.py
firex_keeper/_version.py
firex_keeper/db_model.py
firex_keeper/keeper_event_consumer.py
firex_keeper/keeper_helper.py
firex_keeper/keeper_launcher.py
firex_keeper/persist.py
firex_keeper/task_query.py
firex_keeper-4.1.64.dist-info/LICENSE
firex_keeper-4.1.64.dist-info/METADATA
firex_keeper-4.1.64.dist-info/WHEEL
firex_keeper-4.1.64.dist-info/entry_points.txt
firex_keeper-4.1.64.dist-info/top_level.txt
firex_keeper-4.1.64.dist-info/zip-safe
firex_keeper-4.1.64.dist-info/RECORD
