Metadata-Version: 2.1
Name: firex-keeper
Version: 4.1.64
Summary: FireX event processor for creating an sqlite DB.
Home-page: https://github.com/FireXStuff/firex-keeper
Author: Core FireX Team
Author-email: firex-dev@gmail.com
License: BSD-3-Clause
Platform: UNKNOWN
License-File: LICENSE
Requires-Dist: firexapp
Requires-Dist: SQLAlchemy<2
